bassg/Generator.py
bassg/__init__.py
bassg/__main__.py
bassg-1.2.6.dist-info/LICENSE
bassg-1.2.6.dist-info/METADATA
bassg-1.2.6.dist-info/WHEEL
bassg-1.2.6.dist-info/entry_points.txt
bassg-1.2.6.dist-info/top_level.txt
bassg-1.2.6.dist-info/RECORD
