Metadata-Version: 2.1
Name: bassg
Version: 1.2.6
Summary: BASSG - Basic Agile Static Site Generator
Home-page: https://github.com/hunterlawson/bassg
Author: Hunter Lawson
Author-email: hawson7@gmail.com
License: MIT
Keywords: satic site generator,bassg
Platform: UNKNOWN
Classifier: Programming Language :: Python :: 3
Classifier: License :: OSI Approved :: MIT License
Classifier: Operating System :: OS Independent
License-File: LICENSE
Requires-Dist: beautifulsoup4
Requires-Dist: click
Requires-Dist: Jinja2
Requires-Dist: markdown
